<?xml version="1.0" ?><annotation>
	<folder>train</folder>
	<filename>00183.jpg</filename>
	<path>C:\Users\pc\Desktop\1\JPEGImages\train\00183.jpg</path>
	<source>
		<database>Unknown</database>
	</source>
	<size>
		<width>500</width>
		<height>500</height>
		<depth>3</depth>
	</size>
	<segmented>0</segmented>
	<object>
		<name>pointer</name>
		<pose>Unspecified</pose>
		<truncated>0</truncated>
		<difficult>0</difficult>
		<bndbox>
			<xmin>159</xmin>
			<ymin>138</ymin>
			<xmax>391</xmax>
			<ymax>377</ymax>
		</bndbox>
	</object>
</annotation>