<?xml version="1.0" ?><annotation>
	<folder>train</folder>
	<filename>1241.jpg</filename>
	<path>C:\Users\pc\Desktop\1\JPEGImages\train\1241.jpg</path>
	<source>
		<database>Unknown</database>
	</source>
	<size>
		<width>220</width>
		<height>219</height>
		<depth>3</depth>
	</size>
	<segmented>0</segmented>
	<object>
		<name>pointer</name>
		<pose>Unspecified</pose>
		<truncated>0</truncated>
		<difficult>0</difficult>
		<bndbox>
			<xmin>30</xmin>
			<ymin>72</ymin>
			<xmax>155</xmax>
			<ymax>191</ymax>
		</bndbox>
	</object>
</annotation>