<annotation>
	<folder>point meters</folder>
	<filename>286.jpg</filename>
	<path>C:\Users\FMVPIngram\Desktop\labellmg\电子钟标注\pointer\point meters\286.jpg</path>
	<source>
		<database>Unknown</database>
	</source>
	<size>
		<width>477</width>
		<height>488</height>
		<depth>3</depth>
	</size>
	<segmented>0</segmented>
	<object>
		<name>pointer</name>
		<pose>Unspecified</pose>
		<truncated>0</truncated>
		<difficult>0</difficult>
		<bndbox>
			<xmin>35</xmin>
			<ymin>28</ymin>
			<xmax>451</xmax>
			<ymax>465</ymax>
		</bndbox>
	</object>
</annotation>
