<annotation>
	<folder>point meters</folder>
	<filename>682.jpg</filename>
	<path>C:\Users\FMVPIngram\Desktop\labellmg\电子钟标注\pointer\point meters\682.jpg</path>
	<source>
		<database>Unknown</database>
	</source>
	<size>
		<width>240</width>
		<height>239</height>
		<depth>3</depth>
	</size>
	<segmented>0</segmented>
	<object>
		<name>pointer</name>
		<pose>Unspecified</pose>
		<truncated>0</truncated>
		<difficult>0</difficult>
		<bndbox>
			<xmin>18</xmin>
			<ymin>18</ymin>
			<xmax>218</xmax>
			<ymax>214</ymax>
		</bndbox>
	</object>
</annotation>
